{
  "updated": "2026-06-18T09:15:00",
  "sources_checked": 16,
  "items": [
    {
      "badge": "🟡",
      "date": "2026-06-18",
      "title": "Kane:我们展现了最佳水平",
      "detail": "\"下半场20分钟本可进3-4球\", 点球研究Livakovic→改技术成功, Tuchel:防守需改善",
      "source": "BBC"
    },
    {
      "badge": "🔴",
      "date": "2026-06-18",
      "title": "加纳1-0巴拿马绝杀",
      "detail": "Yirenkyi伤停补时绝杀, Thomas-Asante助攻, 巴拿马心碎, L组出线形势初定",
      "source": "ABC/Yahoo"
    },
    {
      "badge": "🔴",
      "date": "2026-06-18",
      "title": "英格兰4-2克罗地亚开门红",
      "detail": "Kane点射+头球双响, Bellingham 47分闪电破门, Rashford替补锁定, 半场2-2→终场4-2",
      "source": "BBC/EnglandFootball"
    },
    {
      "badge": "🟡",
      "date": "2026-06-17",
      "title": "Ronaldo六届世界杯未破门",
      "detail": "41岁CR7打满全场两度射偏, 未能成首个6届世界杯均进球球员, 葡萄牙中场控制80%但进攻乏力",
      "source": "ESPN"
    },
    {
      "badge": "🔴",
      "date": "2026-06-17",
      "title": "刚果金52年首球创造历史",
      "detail": "Yoane Wissa头球破门→刚果金自1974年来首个世界杯进球, 1-1逼平葡萄牙震惊世界",
      "source": "BBC/FIFA"
    },
    {
      "badge": "🔴",
      "date": "2026-06-17",
      "title": "葡萄牙1-1刚果金爆冷",
      "detail": "Neves 6分头球先拔头筹, Wissa 45+5历史首球扳平, 刚果金52年来世界杯第1分, CR7哑火",
      "source": "FIFA/ESPN/BBC"
    },
    {
      "badge": "🟢",
      "date": "2026-06-17",
      "title": "Opta: Panama优Ghana",
      "detail": "PAN 45.2% vs GHA 29.6%, 模型分歧大",
      "source": "DutchCaribbean"
    },
    {
      "badge": "🟢",
      "date": "2026-06-17",
      "title": "今日裁判公布",
      "detail": "POR-COD:Al-Jassim|ENG-CRO:Turpin|GHA-PAN:Nyberg|UZB-COL:Taylor",
      "source": "FIFA"
    },
    {
      "badge": "🟢",
      "date": "2026-06-17",
      "title": "Day7四场看点",
      "detail": "POR-COD Ronaldo首秀|ENG-CRO焦点战|GHA-PAN出线关键|UZB-COL首秀",
      "source": "FIFA/Yahoo"
    },
    {
      "badge": "🟢",
      "date": "2026-06-17",
      "title": "Mbappe+Haaland领跑金靴",
      "detail": "各2球并列榜首, Messi帽子戏法3球追平, Balogun双响",
      "source": "Yahoo Sports"
    },
    {
      "badge": "🟢",
      "date": "2026-06-17",
      "title": "Scaloni: '享受Messi吧'",
      "detail": "\"他这样已经20年了, 不仅阿根廷人想看, 全世界都想看\"; Mac Allister:\"今天证明没有他不行\"",
      "source": "ESPN"
    },
    {
      "badge": "🟢",
      "date": "2026-06-17",
      "title": "Algeria誓言反弹",
      "detail": "Mahrez:\"就是Messi做了Messi的事\"; 0射正vs阿根廷10射正, 下一场对约旦已成'决定性'",
      "source": "Kansas City Star"
    },
    {
      "badge": "🟢",
      "date": "2026-06-17",
      "title": "Dalic赞Kane世界最佳",
      "detail": "\"他们有世界最好前锋, Kane无所不能\"; Modric:\"Bellingham是现象级, 我不干涉Tuchel决定\"",
      "source": "BBC"
    },
    {
      "badge": "🟢",
      "date": "2026-06-17",
      "title": "CR7追平Messi六届纪录",
      "detail": "41岁Ronaldo第6届世界杯首秀, 对刚果金; Bruno:\"我们都看他踢球长大\"",
      "source": "ESPN"
    },
    {
      "badge": "🟢",
      "date": "2026-06-17",
      "title": "世界杯Day7四场前瞻",
      "detail": "18:00 POR-COD Houston|21:00 ENG-CRO Dallas|00:00 GHA-PAN Toronto|03:00 UZB-COL Mexico City",
      "source": "FIFA"
    },
    {
      "badge": "🟢",
      "date": "2026-06-17",
      "title": "Pokemon预测英格兰胜克罗地亚",
      "detail": "4月龄猩猩Jane选出英格兰胜; Joe Hart:\"Tuchel最坏情况也能赢, 最好情况碾压\"",
      "source": "BBC"
    },
    {
      "badge": "🟡",
      "date": "2026-06-17",
      "title": "Davies几乎确定缺席",
      "detail": "CBC: 对Qatar不上, Bayern不满加拿大冒险",
      "source": "The Globe"
    },
    {
      "badge": "🟡",
      "date": "2026-06-17",
      "title": "Austria 3-1 Jordan",
      "detail": "36年首胜, Schmid+Arnautovic点球",
      "source": "Sky Sports"
    },
    {
      "badge": "🟡",
      "date": "2026-06-17",
      "title": "Argentina 3-0 Algeria",
      "detail": "Messi帽子戏法(修正), Haaland发Snap致敬",
      "source": "Fox Sports"
    },
    {
      "badge": "🟡",
      "date": "2026-06-17",
      "title": "英克大战前瞻",
      "detail": "2018半决赛重演, England 3胜1平1负H2H占优, Kane第30场大赛",
      "source": "BBC/Sporting News"
    },
    {
      "badge": "🟡",
      "date": "2026-06-17",
      "title": "Mbappe: '不在乎批评者'",
      "detail": "\"如果为让批评者闭嘴而踢球, 我得踢到80岁\"; Deschamps:\"允许他上半场消失下半场双响\"",
      "source": "AP/Economic Times"
    },
    {
      "badge": "🟡",
      "date": "2026-06-17",
      "title": "伊拉克Hussein被美海关扣留",
      "detail": "入芝加哥被扣数小时→仍在对挪威进球, Graham Arnold:\"不是政治, 是足球\"",
      "source": "ABC News Australia"
    },
    {
      "badge": "🟡",
      "date": "2026-06-17",
      "title": "奥地利3-1约旦36年首胜",
      "detail": "Schmid世界波+Al Arab乌龙+Arnautovic 90+12点球; Olwan打入约旦世界杯首球",
      "source": "Sky Sports/Al Jazeera"
    },
    {
      "badge": "🟡",
      "date": "2026-06-17",
      "title": "Davies腿筋之谜持续",
      "detail": "加拿大PR:\"鉴于利害关系, 我将不那么透明\"; 队友:\"他必须100%\"; CBC预测几乎确定缺战卡塔尔",
      "source": "Globe and Mail"
    },
    {
      "badge": "🟡",
      "date": "2026-06-17",
      "title": "Yamal伤愈'理想状态'",
      "detail": "De la Fuente确认可首发, 对佛得角替补出场; 18岁天才左腿筋伤愈",
      "source": "FOX Sports"
    },
    {
      "badge": "🟡",
      "date": "2026-06-17",
      "title": "Saliba复出法国防线完整",
      "detail": "背伤愈首发出战塞内加尔, 欧冠决赛后恢复, Deschamps:\"他很好\"",
      "source": "FourFourTwo"
    },
    {
      "badge": "🟡",
      "date": "2026-06-17",
      "title": "英克大战BBC全程直播",
      "detail": "Shearer/Richards/Hart选定首发: Pickford/James/Konsa/Stones/O'Reilly/Rice/Anderson/Madueke/Bellingham/Gordon/Kane",
      "source": "BBC Sport"
    },
    {
      "badge": "🔴",
      "date": "2026-06-17",
      "title": "Messi红牌争议",
      "detail": "ESPN: 100%红牌未判, FIFA被指控保护巨星",
      "source": "Mirror/ESPN"
    },
    {
      "badge": "🔴",
      "date": "2026-06-17",
      "title": "FIFA高官批伊朗待遇",
      "detail": "匿名FIFA理事: 伊朗被'压迫', 强制数小时离境",
      "source": "Observer"
    },
    {
      "badge": "🔴",
      "date": "2026-06-17",
      "title": "Partey上诉被驳回",
      "detail": "加拿大法官拒绝入境, Ghana首战缺核",
      "source": "AP"
    },
    {
      "badge": "🔴",
      "date": "2026-06-17",
      "title": "Livramento OUT",
      "detail": "England后卫小腿伤, Chalobah替换",
      "source": "Sky Sports"
    },
    {
      "badge": "🔴",
      "date": "2026-06-17",
      "title": "Ruben Dias确认缺阵",
      "detail": "Martinez: 不冒险",
      "source": "Fabrizio Romano/Ge.Globo"
    },
    {
      "badge": "🔴",
      "date": "2026-06-17",
      "title": "Ronaldo第6届世界杯首秀",
      "detail": "41岁CR7追平Messi六届纪录, 葡萄牙vs刚果金Houston开战",
      "source": "Fox Sports/Al Jazeera"
    },
    {
      "badge": "🔴",
      "date": "2026-06-17",
      "title": "Messi帽子戏法=Klose16球纪录",
      "detail": "38岁Messi第6届世界杯首戴帽, 追平Klose世界杯16球纪录, 同时追平17胜纪录",
      "source": "ESPN/BBC"
    },
    {
      "badge": "🔴",
      "date": "2026-06-17",
      "title": "Mbappe加冕法国队史射手王",
      "detail": "双响破塞内加尔, 58球超Giroud, 世界杯14球追平Messi, 30码世界波获赞'疯狂'",
      "source": "Sky Sports/BBC"
    },
    {
      "badge": "🔴",
      "date": "2026-06-17",
      "title": "Haaland世界杯首秀双响",
      "detail": "挪威4-1伊拉克, 56/57号国家队进球, 1998年后挪威首场世界杯胜利, 维京战吼响彻看台",
      "source": "AP/ABC"
    },
    {
      "badge": "🔴",
      "date": "2026-06-17",
      "title": "Messi=史上最老帽子戏法",
      "detail": "38岁357天超Ronaldo(33岁)成最年长世界杯戴帽者, 连续5场世界杯进球阿根廷首人",
      "source": "beIN SPORTS"
    },
    {
      "badge": "🔴",
      "date": "2026-06-17",
      "title": "金靴争夺白热化",
      "detail": "Messi 3球领跑, Havertz/Mbappe/Haaland/Balogun/Ayari/Just各2球; 上届金靴Mbappe豪言冲纪录",
      "source": "FIFA/FOX"
    },
    {
      "badge": "🔴",
      "date": "2026-06-17",
      "title": "Neymar确认小组赛全缺",
      "detail": "Grade2小腿撕裂, 5/27后未训练, 巴西队医:仅淘汰赛回归; 球迷怒\"身体已废\"\"为钱入选\"",
      "source": "ESPN/Times of India"
    },
    {
      "badge": "🔴",
      "date": "2026-06-17",
      "title": "Ruben Dias缺战刚果金首战",
      "detail": "Martinez确认'未到100%不冒险', 训练中受伤, 目标6/23对乌兹别克复出",
      "source": "Fabrizio Romano/Tribuna"
    },
    {
      "badge": "🔴",
      "date": "2026-06-17",
      "title": "Trent再次被英格兰无视",
      "detail": "Livramento伤退→选Chalobah不选Trent; Carragher:\"Tuchel优先和谐>实力\"; Maguire:\"避免媒体干扰\"",
      "source": "Mirror/Liverpool.com"
    },
    {
      "badge": "🟢",
      "date": "2026-06-16",
      "title": "Vozinha IG粉丝暴涨100倍",
      "detail": "46,000→5,000,000, 40岁打破最老国家队首秀纪录; 佛得角成第三小参赛国",
      "source": "FIFA"
    },
    {
      "badge": "🟢",
      "date": "2026-06-16",
      "title": "沙特1-1乌拉圭Araujo救主",
      "detail": "Al-Amri先拔头筹, Araujo 80分钟扳平; 沙特换帅后表现超预期",
      "source": "FIFA"
    },
    {
      "badge": "🟢",
      "date": "2026-06-16",
      "title": "伊朗2-2新西兰政治阴影下",
      "detail": "Just梅开二度+伊朗两度扳平, Taremi公开批评FIFA:\"世界杯体验被政治破坏\"",
      "source": "FIFA/Akashvani"
    },
    {
      "badge": "🟡",
      "date": "2026-06-16",
      "title": "France 3-1 Senegal",
      "detail": "Mbappe双响+世界波",
      "source": "BBC"
    },
    {
      "badge": "🟡",
      "date": "2026-06-16",
      "title": "Norway 4-1 Iraq",
      "detail": "Haaland双响, Norway I组榜首",
      "source": "ABC"
    },
    {
      "badge": "🟡",
      "date": "2026-06-16",
      "title": "西班牙连续4场不胜",
      "detail": "自2022年对日本11分钟后未进球, 49射+2500传无果; De la Fuente:\"难以置信地困难\"",
      "source": "Sky Sports"
    },
    {
      "badge": "🟡",
      "date": "2026-06-16",
      "title": "比利时1-1埃及",
      "detail": "Ashour世界波+卢卡库替补秒扳平, Salah生日无进球, Courtois神扑+门柱拒De Bruyne",
      "source": "Irish Independent"
    },
    {
      "badge": "🔴",
      "date": "2026-06-16",
      "title": "佛得角0-0西班牙=史上最大冷门",
      "detail": "人口<50万岛国首秀逼平欧洲冠军, 西班牙27射0球, 40岁Vozinha封神, 赛后痛哭",
      "source": "Sky Sports/FIFA"
    },
    {
      "badge": "🟢",
      "date": "2026-06-15",
      "title": "Koeman: '不后悔换人'",
      "detail": "\"足球就是有趣, 日本进球后也开始防守\"; 荷兰0.78xG vs 日本0.59xG, 两队皆不满意",
      "source": "FotMob"
    },
    {
      "badge": "🟢",
      "date": "2026-06-15",
      "title": "Neuer创德国最老出场纪录",
      "detail": "40岁79天超Matthaus, 德国12年来首次世界杯开门红",
      "source": "FIFA"
    },
    {
      "badge": "🟡",
      "date": "2026-06-15",
      "title": "日本89分钟绝平荷兰2-2",
      "detail": "Kamada替补头球折射绝平, Van Dijk+Summerville两度领先; 日本球迷涉谷狂欢庆祝",
      "source": "FIFA/Sky Sports"
    },
    {
      "badge": "🟡",
      "date": "2026-06-15",
      "title": "瑞典5-1突尼斯Isak传射",
      "detail": "Isak 1球2助, Ayari双响, 瑞典F组领跑; 突尼斯队长Skhiri失误送礼",
      "source": "Daily Mail"
    },
    {
      "badge": "🔴",
      "date": "2026-06-15",
      "title": "德国7-1库拉索",
      "detail": "Havertz双响+Nmecha世界波+Musiala闪击, 库拉索Comenencia打入历史首球, Undav 8.9分全场最佳",
      "source": "DFB/FIFA"
    },
    {
      "badge": "🟢",
      "date": "2026-06-14",
      "title": "美国4-1巴拉圭Pulisic伤退",
      "detail": "Balogun双响, Pulisic半场小腿被撞换下, 预防性措施, 备战澳大利亚day-to-day",
      "source": "Yahoo/FOX"
    },
    {
      "badge": "🟢",
      "date": "2026-06-14",
      "title": "澳大利亚2-0土耳其Irankunda创纪录",
      "detail": "20岁世界杯最年轻进球纪录, Beach 8次扑救, Socceroo爆冷零封",
      "source": "ABC"
    },
    {
      "badge": "🟢",
      "date": "2026-06-14",
      "title": "科特迪瓦1-0厄瓜多尔Amad绝杀",
      "detail": "Amad替补绝杀, 象牙海岸非洲军团连胜势头",
      "source": "FIFA"
    },
    {
      "badge": "🟡",
      "date": "2026-06-14",
      "title": "巴西1-1摩洛哥Neymar缺阵",
      "detail": "Ancelotti无Neymar首秀, 摩洛哥顽强逼平, Neymar目标淘汰赛复出",
      "source": "ESPN"
    }
  ]
}